{"identifier":"maidkun/buttplug-editor/project","version":1,"workspace":{"boards":[{"state":{"nodes":[{"type":"WaveGenerator","id":"node_160967437089010","name":"Wave Generator","options":[["Wave Type",1],["Only Positive Wave",true]],"state":{},"interfaces":[["Time",{"id":"ni_160967437089111","value":0}],["Amplitude",{"id":"ni_160967437089112","value":0.5}],["Frequency",{"id":"ni_160967437089113","value":0.2}],["Output",{"id":"ni_160967437089114","value":0.09809232249637934}]],"position":{"x":32,"y":308},"width":200,"twoColumn":false},{"type":"Vibrator","id":"node_160967437589015","name":"Vibrator","options":[["Vibrator",null]],"state":{},"interfaces":[["Value",{"id":"ni_160967437589016","value":0.09809232249637934}]],"position":{"x":427,"y":223},"width":200,"twoColumn":false},{"type":"VisualizeWave","id":"node_160967437817917","name":"Wave Visualizer","options":[["Result",{"value":0.09809232249637934,"time":44.25699996948242}]],"state":{},"interfaces":[["Value",{"id":"ni_160967437817918","value":0.09809232249637934}]],"position":{"x":425,"y":390},"width":200,"twoColumn":false}],"connections":[{"id":"160967438284321","from":"ni_160967437089114","to":"ni_160967437589016"},{"id":"160967438472124","from":"ni_160967437089114","to":"ni_160967437817918"}],"panning":{"x":235,"y":45},"scaling":1}}]},"components":[{"origin":"core","name":"WaveGenerator","inputPorts":[],"outputPorts":[]},{"origin":"core","name":"Vibrator","inputPorts":[],"outputPorts":[]},{"origin":"core","name":"VisualizeWave","inputPorts":[],"outputPorts":[]}]}